LICENSE.rst
MANIFEST.in
README.rst
setup.py
mozilla_logger/__init__.py
mozilla_logger/log.py
mozilla_logger/tests.py
mozilla_logger.egg-info/PKG-INFO
mozilla_logger.egg-info/SOURCES.txt
mozilla_logger.egg-info/dependency_links.txt
mozilla_logger.egg-info/not-zip-safe
mozilla_logger.egg-info/top_level.txt