Metadata-Version: 1.0
Name: mozilla-logger
Version: 0.2
Summary: Django interface with statsd
Home-page: https://github.com/andymckay/mozilla-logger
Author: Andy McKay
Author-email: andym@mozilla.com
License: MPL
Platform: UNKNOWN
Classifier: Intended Audience :: Developers
Classifier: Natural Language :: English
Classifier: Operating System :: OS Independent
Classifier: Framework :: Django
